{
  "lod": 1,
  "generatedAt": "2026-02-14T19:26:34.170Z",
  "contract": {
    "manifestVersion": "territories-bake-v1",
    "packageId": "territories-bake-2026-02-14T19:26:33.851Z",
    "topologyGraphHash": "33d3ef481de6f264bce71de68a9339685deb2aa4ba749e6273ecd26a3379a30e"
  },
  "chunkTriangleBudget": 1800,
  "chunks": [
    {
      "id": "chunk-000",
      "partIds": [
        "ZWE",
        "ZMB",
        "YEM",
        "VNM",
        "VEN",
        "VAT",
        "VUT:0-0",
        "VUT:1-0",
        "UZB",
        "URY",
        "FSM",
        "MHL",
        "MNP",
        "VIR",
        "GUM",
        "ASM",
        "PRI",
        "USA:0-0",
        "USA:1-0",
        "USA:2-0",
        "USA:3-0",
        "USA:4-0",
        "USA:5-0",
        "USA:6-0",
        "USA:7-0",
        "USA:8-0",
        "USA:9-0",
        "USA:10-0",
        "USA:11-0",
        "USA:12-0",
        "USA:13-0",
        "SGS",
        "IOT",
        "SHN",
        "PCN",
        "AIA",
        "FLK:0-0",
        "FLK:1-0",
        "CYM",
        "BMU",
        "VGB",
        "TCA",
        "MSR",
        "JEY",
        "GGY",
        "IMN",
        "GBR:0-0",
        "GBR:1-0",
        "ARE",
        "UKR",
        "UGA",
        "TKM",
        "TUR:0-0",
        "TUR:1-0",
        "TUN",
        "TTO",
        "TON",
        "TGO",
        "TLS",
        "THA",
        "TZA",
        "TJK",
        "TWN",
        "SYR",
        "CHE",
        "SWE:0-0",
        "SWE:1-0",
        "SWZ",
        "SUR",
        "SDS",
        "SDN",
        "LKA",
        "ESP:0-0",
        "ESP:1-0",
        "ESP:2-0",
        "KOR",
        "ZAF"
      ],
      "partCount": 77,
      "vertexCount": 1930,
      "triangleCount": 1769
    },
    {
      "id": "chunk-001",
      "partIds": [
        "SOM",
        "SOL",
        "SLB:0-0",
        "SLB:1-0",
        "SLB:2-0",
        "SLB:3-0",
        "SVK",
        "SVN",
        "SGP",
        "SLE",
        "SYC",
        "SRB",
        "SEN",
        "SAU",
        "STP",
        "SMR",
        "WSM",
        "VCT",
        "LCA",
        "KNA",
        "RWA",
        "RUS:0-0",
        "RUS:1-0",
        "RUS:2-0",
        "RUS:3-0",
        "RUS:4-0",
        "RUS:5-0",
        "RUS:6-0",
        "RUS:7-0",
        "RUS:8-0",
        "RUS:9-0",
        "RUS:10-0",
        "RUS:11-0",
        "RUS:12-0",
        "RUS:13-0",
        "RUS:14-0",
        "RUS:15-0",
        "RUS:16-0",
        "RUS:17-0",
        "RUS:18-0",
        "RUS:19-0",
        "RUS:20-0",
        "RUS:21-0",
        "RUS:22-0",
        "ROU",
        "QAT",
        "PRT",
        "POL",
        "PHL:0-0",
        "PHL:1-0",
        "PHL:2-0",
        "PHL:3-0",
        "PHL:4-0",
        "PHL:5-0",
        "PHL:6-0",
        "PHL:7-0",
        "PHL:8-0",
        "PHL:9-0",
        "PER",
        "PRY",
        "PNG:0-0",
        "PNG:1-0",
        "PNG:2-0",
        "PNG:3-0",
        "PAN",
        "PLW",
        "PAK",
        "OMN",
        "NOR:0-0",
        "NOR:1-0",
        "NOR:2-0",
        "NOR:3-0",
        "PRK",
        "NGA",
        "NER",
        "NIC"
      ],
      "partCount": 76,
      "vertexCount": 1966,
      "triangleCount": 1800
    },
    {
      "id": "chunk-002",
      "partIds": [
        "NZL:0-0",
        "NZL:1-0",
        "NIU",
        "COK",
        "NLD:0-0",
        "NLD:1-0",
        "ABW",
        "CUW",
        "NPL",
        "NRU",
        "NAM",
        "MOZ",
        "MAR",
        "SAH",
        "MNE",
        "MNG",
        "MDA",
        "MCO",
        "MEX",
        "MUS",
        "MRT",
        "MLT",
        "MLI",
        "MDV",
        "MYS:0-0",
        "MYS:1-0",
        "MWI",
        "MDG",
        "MKD",
        "LUX",
        "LTU",
        "LIE",
        "LBY",
        "LBR",
        "LSO",
        "LBN",
        "LVA",
        "LAO",
        "KGZ",
        "KWT",
        "KOS",
        "KIR",
        "KEN",
        "KAZ",
        "JOR",
        "JPN:0-0",
        "JPN:1-0",
        "JPN:2-0",
        "JPN:3-0",
        "JAM",
        "ITA:0-0",
        "ITA:1-0",
        "ITA:2-0",
        "ISR",
        "PSX:0-0",
        "PSX:1-0",
        "IRL",
        "IRQ",
        "IRN",
        "IDN:0-0",
        "IDN:1-0",
        "IDN:2-0",
        "IDN:3-0",
        "IDN:4-0",
        "IDN:5-0",
        "IDN:6-0",
        "IDN:7-0",
        "IDN:8-0",
        "IDN:9-0",
        "IDN:10-0",
        "IDN:11-0",
        "IDN:12-0",
        "IDN:13-0",
        "IDN:14-0",
        "IDN:15-0"
      ],
      "partCount": 75,
      "vertexCount": 1944,
      "triangleCount": 1793
    },
    {
      "id": "chunk-003",
      "partIds": [
        "IDN:16-0",
        "IDN:17-0",
        "IDN:18-0",
        "IDN:19-0",
        "IDN:20-0",
        "IDN:21-0",
        "IDN:22-0",
        "IDN:23-0",
        "IDN:24-0",
        "IDN:25-0",
        "IDN:26-0",
        "IDN:27-0",
        "IDN:28-0",
        "IND",
        "ISL",
        "HUN",
        "HND",
        "HTI",
        "GUY",
        "GNB",
        "GIN",
        "GTM",
        "GRD",
        "GRC:0-0",
        "GRC:1-0",
        "GRC:2-0",
        "GHA",
        "DEU",
        "GEO",
        "GMB",
        "GAB",
        "FRA:0-0",
        "FRA:1-0",
        "FRA:2-0",
        "FRA:3-0",
        "SPM",
        "WLF",
        "MAF",
        "BLM",
        "PYF",
        "NCL",
        "ATF",
        "ALD",
        "FIN",
        "FJI:0-0",
        "FJI:1-0",
        "ETH",
        "EST:0-0",
        "EST:1-0",
        "ERI",
        "GNQ:0-0",
        "GNQ:1-0",
        "SLV",
        "EGY",
        "ECU:0-0",
        "ECU:1-0",
        "DOM",
        "DMA",
        "DJI",
        "GRL:0-0",
        "GRL:1-0",
        "GRL:2-0",
        "FRO",
        "DNK:0-0",
        "DNK:1-0",
        "DNK:2-0",
        "CZE",
        "CYN",
        "CYP",
        "CUB:0-0",
        "CUB:1-0",
        "HRV:0-0",
        "HRV:1-0",
        "CIV",
        "CRI",
        "COD",
        "COG",
        "COM",
        "COL"
      ],
      "partCount": 79,
      "vertexCount": 1950,
      "triangleCount": 1792
    },
    {
      "id": "chunk-004",
      "partIds": [
        "CHN:0-0",
        "CHN:1-0",
        "MAC",
        "HKG",
        "CHL:0-0",
        "CHL:1-0",
        "CHL:2-0",
        "CHL:3-0",
        "CHL:4-0",
        "CHL:5-0",
        "CHL:6-0",
        "CHL:7-0",
        "CHL:8-0",
        "CHL:9-0",
        "TCD",
        "CAF",
        "CPV",
        "CAN:0-0",
        "CAN:1-0",
        "CAN:2-0",
        "CAN:3-0",
        "CAN:4-0",
        "CAN:5-0",
        "CAN:6-0",
        "CAN:7-0",
        "CAN:8-0",
        "CAN:9-0",
        "CAN:10-0",
        "CAN:11-0",
        "CAN:12-0",
        "CAN:13-0",
        "CAN:14-0",
        "CAN:15-0",
        "CAN:16-0",
        "CAN:17-0",
        "CAN:18-0",
        "CAN:19-0",
        "CAN:20-0",
        "CAN:21-0",
        "CAN:22-0",
        "CAN:23-0",
        "CAN:24-0",
        "CAN:25-0",
        "CAN:26-0",
        "CAN:27-0",
        "CAN:28-0",
        "CAN:29-0",
        "CAN:30-0",
        "CAN:31-0",
        "CAN:32-0",
        "CAN:33-0",
        "CAN:34-0",
        "CAN:35-0",
        "CMR",
        "KHM",
        "MMR",
        "BDI",
        "BFA",
        "BGR",
        "BRN"
      ],
      "partCount": 60,
      "vertexCount": 1712,
      "triangleCount": 1566
    },
    {
      "id": "chunk-005",
      "partIds": [
        "BRA:0-0",
        "BRA:1-0",
        "BRA:2-0",
        "BWA",
        "BIH",
        "BOL",
        "BTN",
        "BEN",
        "BLZ",
        "BEL",
        "BLR",
        "BRB",
        "BGD",
        "BHR",
        "BHS:0-0",
        "BHS:1-0",
        "AZE:0-0",
        "AZE:1-0",
        "AUT",
        "AUS:0-0",
        "AUS:1-0",
        "AUS:2-0",
        "AUS:3-0",
        "AUS:4-0",
        "IOA",
        "HMD",
        "NFK",
        "ATC",
        "ARM",
        "ARG:0-0",
        "ARG:1-0",
        "ATG",
        "AGO:0-0",
        "AGO:1-0",
        "AND",
        "DZA",
        "ALB",
        "AFG",
        "KAS",
        "ATA:0-0",
        "ATA:1-0",
        "ATA:2-0",
        "ATA:3-0",
        "ATA:4-0",
        "ATA:5-0",
        "ATA:6-0",
        "ATA:7-0",
        "ATA:8-0",
        "ATA:9-0",
        "ATA:10-0",
        "ATA:11-0",
        "ATA:12-0",
        "ATA:13-0",
        "SXM",
        "TUV"
      ],
      "partCount": 55,
      "vertexCount": 1798,
      "triangleCount": 1655
    }
  ]
}